__init__.py
jsonistyping/__init__.py
jsonistyping/errors/__init__.py
jsonistyping/errors/validation.py
jsonistyping/input/__init__.py
jsonistyping/input/base.py
jsonistyping/output/__init__.py
jsonistyping/output/base.py
jsonistyping-0.1.2.dist-info/LICENSE.md
jsonistyping-0.1.2.dist-info/METADATA
jsonistyping-0.1.2.dist-info/WHEEL
jsonistyping-0.1.2.dist-info/top_level.txt
jsonistyping-0.1.2.dist-info/RECORD
